cooldowns/__init__.py
cooldowns/buckets/__init__.py
cooldowns/buckets/hashable_arguments.py
cooldowns/buckets/main.py
cooldowns/buckets/slash.py
cooldowns/cooldown.py
cooldowns/cooldown_times_per.py
cooldowns/date_util.py
cooldowns/exceptions.py
cooldowns/persistence.py
cooldowns/protocols/__init__.py
cooldowns/protocols/bucket.py
cooldowns/static_cooldown.py
cooldowns/static_times_per.py
cooldowns/utils.py
function_cooldowns-2.2.0.dist-info/LICENSE
function_cooldowns-2.2.0.dist-info/METADATA
function_cooldowns-2.2.0.dist-info/WHEEL
function_cooldowns-2.2.0.dist-info/RECORD
