Metadata-Version: 2.3
Name: function-cooldowns
Version: 2.2.0
Summary: A simplistic decorator based approach to rate limiting function calls.
License: Unlicense
Author: Skelmis
Author-email: skelmis.craft@gmail.com
Requires-Python: >=3.10,<4.0
Classifier: Programming Language :: Python :: 3
Classifier: License :: OSI Approved :: MIT License
Classifier: Operating System :: OS Independent
Requires-Dist: attrs (>=25.1.0,<26.0.0)
Project-URL: Documentation, https://function-cooldowns.rtfd.io/
Project-URL: Homepage, https://github.com/Skelmis/Function-Cooldowns
Project-URL: Issue tracker, https://github.com/Skelmis/Function-Cooldowns/issues
